kwkey/__init__.py
kwkey/duality.py
kwkey/example_jfine.py
kwkey/jfine.py
kwkey/sdaprano.py
kwkey/test.py
kwkey/test_K.py
kwkey/test_duality.py
kwkey/test_jfine.py
kwkey/test_sdaprano.py
kwkey/tools.py
kwkey-0.0.2.dist-info/LICENSE
kwkey-0.0.2.dist-info/METADATA
kwkey-0.0.2.dist-info/WHEEL
kwkey-0.0.2.dist-info/top_level.txt
kwkey-0.0.2.dist-info/RECORD
