Metadata-Version: 2.1
Name: kwkey
Version: 0.0.2
Summary: Indexing with keyword arguments
Home-page: https://github.com/jfine2358/python-kwkey
Author: Jonathan Fine
Author-email: jfine2358@gmail.com
License: UNKNOWN
Platform: UNKNOWN
Classifier: Programming Language :: Python :: 3
Classifier: License :: OSI Approved :: MIT License
Classifier: Operating System :: OS Independent
Requires-Python: >=3.6
